osrsreboxed/__init__.py
osrsreboxed/docs/items-complete.json
osrsreboxed/docs/monsters-complete.json
osrsreboxed/docs/prayers-complete.json
osrsreboxed/items_api/__init__.py
osrsreboxed/items_api/all_items.py
osrsreboxed/items_api/item_equipment.py
osrsreboxed/items_api/item_properties.py
osrsreboxed/items_api/item_weapon.py
osrsreboxed/items_api_examples/generate_chunktracker_data.py
osrsreboxed/items_api_examples/generate_invalid_items.py
osrsreboxed/items_api_examples/guess_the_item_game.py
osrsreboxed/items_api_examples/items_to_csv.py
osrsreboxed/items_api_examples/lookup_methods_examples.py
osrsreboxed/items_api_examples/print_all_items.py
osrsreboxed/items_api_examples/print_f2p_weapons.py
osrsreboxed/items_api_examples/print_highest_prayer_items.py
osrsreboxed/items_api_examples/print_highest_slash_bonus.py
osrsreboxed/items_api_examples/print_sort_item_releases.py
osrsreboxed/monsters_api/__init__.py
osrsreboxed/monsters_api/all_monsters.py
osrsreboxed/monsters_api/monster_drop.py
osrsreboxed/monsters_api/monster_properties.py
osrsreboxed/monsters_api_examples/find_rarest_drops.py
osrsreboxed/monsters_api_examples/print_all_monsters.py
osrsreboxed/monsters_api_examples/print_slayer_tasks.py
osrsreboxed/monsters_api_examples/search_monster_drops.py
osrsreboxed/monsters_api_examples/test_drops_rarity.py
osrsreboxed/prayers_api/__init__.py
osrsreboxed/prayers_api/all_prayers.py
osrsreboxed/prayers_api/prayer_properties.py
osrsreboxed-2.3.33.dist-info/LICENSE
osrsreboxed-2.3.33.dist-info/METADATA
osrsreboxed-2.3.33.dist-info/WHEEL
osrsreboxed-2.3.33.dist-info/RECORD
