Metadata-Version: 2.1
Name: osrsreboxed
Version: 2.3.33
Summary: A complete and up-to-date database of Old School Runescape (OSRS) items, monsters and prayers accessible using a Python API.
Home-page: https://github.com/0xNeffarion/osrsreboxed-db
License: GPL-3.0-only
Author: Neffarion
Author-email: main@neffware.com
Requires-Python: >=3.7,<4.0
Classifier: License :: OSI Approved :: GNU General Public License v3 (GPLv3)
Classifier: Programming Language :: Python :: 3
Classifier: Programming Language :: Python :: 3.7
Classifier: Programming Language :: Python :: 3.8
Classifier: Programming Language :: Python :: 3.9
Classifier: Programming Language :: Python :: 3.10
Classifier: Programming Language :: Python :: 3.11
Requires-Dist: dataclasses (>=0,<1)
Requires-Dist: setuptools (==60.0.0)
Project-URL: Repository, https://github.com/0xNeffarion/osrsreboxed-db
